rubino_rubika/__init__.py
rubino_rubika/meth/__init__.py
rubino_rubika/server/__init__.py
rubino_rubika-0.0.2.dist-info/LICENSE
rubino_rubika-0.0.2.dist-info/METADATA
rubino_rubika-0.0.2.dist-info/WHEEL
rubino_rubika-0.0.2.dist-info/top_level.txt
rubino_rubika-0.0.2.dist-info/RECORD
