Metadata-Version: 2.1
Name: rubino-rubika
Version: 0.0.2
Summary: The most complete Rubino rubika library
Author-email: AmirErshadi <ershadia317@gmail.com>
Project-URL: Homepage, https://rubika.ir/amir_ershadi_2
Project-URL: Bug Tracker, https://rubika.ir/amir_ershadi_2
Classifier: Programming Language :: Python :: 3
Classifier: License :: OSI Approved :: MIT License
Classifier: Operating System :: OS Independent
Requires-Python: >=3.7
License-File: LICENSE
